{
  "$schema": "https://schema.management.azure.com/schemas/2019-04-01/deploymentTemplate.json#",
  "contentVersion": "1.0.0.0",
  "parameters": {
    "storageAccountName": {
      "type": "string"
    },
    "location": {
      "type": "string"
    }
  },
  "resources": [
    {
      "type": "Microsoft.Storage/storageAccounts",
      "apiVersion": "2022-09-01",
      "name": "[parameters('storageAccountName')]",
      "location": "[parameters('location')]",
      "kind": "StorageV2",
      "sku": {
        "name": "Standard_LRS"
      },
      "properties": {
        "dnsEndpointType": "Standard",
        "defaultToOAuthAuthentication": false,
        "publicNetworkAccess": "Enabled",
        "allowCrossTenantReplication": false,
        "minimumTlsVersion": "TLS1_2",
        "allowBlobPublicAccess": false,
        "allowSharedKeyAccess": true,
        "largeFileSharesState": "Enabled",
        "isHnsEnabled": true,
        "supportsHttpsTrafficOnly": true,
        "accessTier": "Hot",
        "networkAcls": {
          "bypass": "AzureServices",
          "virtualNetworkRules": [],
          "ipRules": [],
          "defaultAction": "Allow"
        },
        "encryption": {
          "keySource": "Microsoft.Storage",
          "services": {
            "blob": {
              "enabled": true
            },
            "file": {
              "enabled": true
            }
          }
        }
      }
    },
    {
      "type": "Microsoft.Storage/storageAccounts/blobServices/containers",
      "apiVersion": "2022-09-01",
      "name": "[concat(parameters('storageAccountName'), '/default/input')]",
      "dependsOn": [
        "[resourceId('Microsoft.Storage/storageAccounts', parameters('storageAccountName'))]"
      ],
      "properties": {
        "publicAccess": "None"
      }
    }
  ]
}
